{
  "last_updated": "2025-11-30T00:55:32.399312+00:00Z",
  "check_now": {
    "count": 0,
    "severity_breakdown": {},
    "files": [],
    "preview": "No immediate issues"
  },
  "mention_if_relevant": {
    "count": 135,
    "categories": {
      "E402": 44,
      "F401": 31,
      "F841": 32,
      "F541": 8,
      "general": 20
    },
    "summary": "44 E402, 31 F401, 32 F841, 8 F541, 20 general"
  },
  "deferred": {
    "count": 0,
    "summary": "0 background items"
  },
  "auto_fixed": {
    "count": 0,
    "summary": "0 items auto-fixed"
  }
}